qetrader/__init__.py
qetrader/prodtables.py
qetrader/qeaccount.py
qetrader/qearbit.py
qetrader/qeasyncdata.py
qetrader/qeasyncstrat.py
qetrader/qebacktestmul.py
qetrader/qecontext.py
qetrader/qectpconst_wrap.py
qetrader/qectpmarket.py
qetrader/qectpmarket_wrap.py
qetrader/qectptrader.py
qetrader/qectptrader_wrap.py
qetrader/qeglobal.py
qetrader/qehtstrader.py
qetrader/qeinterface.py
qetrader/qelogger.py
qetrader/qemain.py
qetrader/qemonitor_log_web.py
qetrader/qeoption.py
qetrader/qeplugins.py
qetrader/qeredisdb.py
qetrader/qeriskctl.py
qetrader/qesimtrader.py
qetrader/qestatistics.py
qetrader/qestockmarket.py
qetrader/qestratmarket_wrap.py
qetrader/qestratprocess.py
qetrader/qesysconf.py
qetrader/qetype.py
qetrader/qeudpclient.py
qetrader/qeweb.py
qetrader/sysconfig.json
qetrader/linux/qestockmarket.py
qetrader/linux/pytransform/__init__.py
qetrader/linux/pytransform/_pytransform.so
qetrader/static/canvas.js
qetrader/static/jquery.pagination.js
qetrader/static/jquery.timers.js
qetrader/static/theme.css
qetrader/templates/backtest.html
qetrader/templates/base.html
qetrader/templates/fundhome.html
qetrader/templates/image_all.html
qetrader/templates/image_ex.html
qetrader/win/qestockmarket.py
qetrader/win/pytransform/__init__.py
qetrader/win/pytransform/_pytransform.dll
qetrader-1.0.37.dist-info/LICENSE
qetrader-1.0.37.dist-info/METADATA
qetrader-1.0.37.dist-info/WHEEL
qetrader-1.0.37.dist-info/top_level.txt
qetrader-1.0.37.dist-info/RECORD
