Metadata-Version: 2.1
Name: qetrader
Version: 1.0.37
Summary: Quantease Trader SDK for quants
Author-email: Scott Zhang <scott2011@qq.com>
License: MIT License
Project-URL: Homepage, https://github.com/quantease/qetrader
Project-URL: Bug Tracker, https://github.com/quantease/qetrader/issues
Classifier: Programming Language :: Python :: 3
Classifier: License :: OSI Approved :: MIT License
Classifier: Operating System :: OS Independent
Requires-Python: >=3.7
License-File: LICENSE
Requires-Dist: chinese-calendar >=1.9.0
Requires-Dist: Cython >=0.29.33
Requires-Dist: ctpwrapper >=6.6.9
Requires-Dist: Flask >=1.1.1
Requires-Dist: Flask-Bootstrap >=3.3.7.1
Requires-Dist: Flask-Compress >=1.12
Requires-Dist: matplotlib >=3.1.0
Requires-Dist: nest-asyncio >=1.5.5
Requires-Dist: numpy >=1.19.2
Requires-Dist: pandas >=1.3.5
Requires-Dist: python-dateutil >=2.8.2
Requires-Dist: qesdk >=0.0.15
Requires-Dist: quantstats >=0.0.59
Requires-Dist: redis >=4.3.4
Requires-Dist: scipy >=1.7.3
Requires-Dist: passlib >=1.7.4
